wollok_kernel/__init__.py
wollok_kernel/__main__.py
wollok_kernel/kernel.py
wollok_kernel/wollok_bridge/__init__.py
wollok_kernel/wollok_bridge/library.py
wollok_kernel/wollok_bridge/package-lock.json
wollok_kernel/wollok_bridge/package.json
wollok_kernel/wollok_bridge/wollok.js
wollok_kernel/wollok_bridge/polyfills/crypto/index.js
wollok_kernel/wollok_bridge/node_modules/.package-lock.json
wollok_kernel/wollok_bridge/node_modules/.bin/uuid
wollok_kernel/wollok_bridge/node_modules/@types/parsimmon/LICENSE
wollok_kernel/wollok_bridge/node_modules/@types/parsimmon/README.md
wollok_kernel/wollok_bridge/node_modules/@types/parsimmon/index.d.ts
wollok_kernel/wollok_bridge/node_modules/@types/parsimmon/package.json
wollok_kernel/wollok_bridge/node_modules/crypto/index.js
wollok_kernel/wollok_bridge/node_modules/infestines/CHANGELOG.md
wollok_kernel/wollok_bridge/node_modules/infestines/LICENSE.md
wollok_kernel/wollok_bridge/node_modules/infestines/README.md
wollok_kernel/wollok_bridge/node_modules/infestines/package.json
wollok_kernel/wollok_bridge/node_modules/infestines/dist/infestines.cjs.js
wollok_kernel/wollok_bridge/node_modules/infestines/dist/infestines.es.js
wollok_kernel/wollok_bridge/node_modules/infestines/dist/infestines.js
wollok_kernel/wollok_bridge/node_modules/infestines/dist/infestines.min.js
wollok_kernel/wollok_bridge/node_modules/infestines/src/infestines.js
wollok_kernel/wollok_bridge/node_modules/parsimmon/LICENSE
wollok_kernel/wollok_bridge/node_modules/parsimmon/README.md
wollok_kernel/wollok_bridge/node_modules/parsimmon/package.json
wollok_kernel/wollok_bridge/node_modules/parsimmon/build/parsimmon.umd.min.js
wollok_kernel/wollok_bridge/node_modules/parsimmon/src/parsimmon.js
wollok_kernel/wollok_bridge/node_modules/partial.lenses/CHANGELOG.md
wollok_kernel/wollok_bridge/node_modules/partial.lenses/EXERCISES.md
wollok_kernel/wollok_bridge/node_modules/partial.lenses/IMPLEMENTATION.md
wollok_kernel-1.6.dist-info/METADATA
wollok_kernel-1.6.dist-info/WHEEL
wollok_kernel-1.6.dist-info/licenses/LICENSE
wollok_kernel-1.6.dist-info/RECORD
