Metadata-Version: 2.4
Name: wollok-kernel
Version: 1.6
Summary: Wollok kernel for Jupyter
Project-URL: Homepage, https://github.com/jupyter/wollok-kernel
Author-email: Jupyter Development Team <jupyter@googlegroups.com>
License: GNU GENERAL PUBLIC LICENSE 
License-File: LICENSE
Classifier: Intended Audience :: Developers
Classifier: License :: OSI Approved :: GNU General Public License v3 or later (GPLv3+)
Classifier: Programming Language :: Python :: 3
Requires-Python: >=3.8
Requires-Dist: ipykernel
Requires-Dist: jupyter-client
Requires-Dist: pythonmonkey
Provides-Extra: test
Requires-Dist: jupyter-kernel-test; extra == 'test'
